scramblery/__init__.py
scramblery/scramblery.py
scramblery-1.2.5.dist-info/METADATA
scramblery-1.2.5.dist-info/WHEEL
scramblery-1.2.5.dist-info/RECORD
