Metadata-Version: 2.1
Name: scramblery
Version: 1.2.5
Summary: 
Home-page: https://github.com/altunenes/scramblery
License: MIT
Keywords: scramblery,scramble,face scramble,psychology,experimental psychology,altunenes
Author: altunenes
Author-email: enesaltun2@gmail.com
Requires-Python: >=3.8,<4.0
Classifier: License :: OSI Approved :: MIT License
Classifier: Operating System :: OS Independent
Classifier: Programming Language :: Python :: 3
Classifier: Programming Language :: Python :: 3.8
Classifier: Programming Language :: Python :: 3.9
Classifier: Programming Language :: Python :: 3.10
Classifier: Programming Language :: Python :: 3.11
Classifier: Programming Language :: Python :: 3
Classifier: Programming Language :: Python :: 3.6
Classifier: Programming Language :: Python :: 3.7
Classifier: Programming Language :: Python :: 3.8
Classifier: Programming Language :: Python :: 3.9
Project-URL: Repository, https://github.com/altunenes/scramblery
